abmjktmyhellopkg/__init__.py
abmjktmyhellopkg/hello.py
abmjktmyhellopkg-0.0.9.dist-info/METADATA
abmjktmyhellopkg-0.0.9.dist-info/WHEEL
abmjktmyhellopkg-0.0.9.dist-info/top_level.txt
abmjktmyhellopkg-0.0.9.dist-info/RECORD
