Metadata-Version: 2.1
Name: abmjktmyhellopkg
Version: 0.0.9
Summary: Test create package
Home-page: UNKNOWN
Author: dhonyabumuhammad (Jakarta)
Author-email: <dp20bp@gmail.com>
License: UNKNOWN
Keywords: hellohello
Platform: UNKNOWN
Classifier: Development Status :: 1 - Planning
Classifier: Intended Audience :: Developers
Classifier: Programming Language :: Python :: 3
Classifier: Operating System :: Unix
Classifier: Operating System :: MacOS :: MacOS X
Classifier: Operating System :: Microsoft :: Windows
